pytest_richtrace/__init__.py
pytest_richtrace/collection_observer.py
pytest_richtrace/console.py
pytest_richtrace/event.py
pytest_richtrace/events.py
pytest_richtrace/item.py
pytest_richtrace/plugin.py
pytest_richtrace/py.typed
pytest_richtrace/results.py
pytest_richtrace/rich_reporter.py
pytest_richtrace/test_execution_observer.py
pytest_richtrace-0.2.1.dist-info/METADATA
pytest_richtrace-0.2.1.dist-info/WHEEL
pytest_richtrace-0.2.1.dist-info/entry_points.txt
pytest_richtrace-0.2.1.dist-info/RECORD
