Metadata-Version: 2.1
Name: pytest-richtrace
Version: 0.2.1
Summary: A pytest plugin that displays the names and information of the pytest hook functions as they are executed.
License: Apache-2.0
Author: Simon Kennedy
Author-email: sffjunkie+code@gmail.com
Requires-Python: >=3.11,<4.0
Classifier: License :: OSI Approved :: Apache Software License
Classifier: Programming Language :: Python :: 3
Classifier: Programming Language :: Python :: 3.11
Requires-Dist: pydantic (>=2.0a1)
Requires-Dist: rich (>=13.3.5,<14.0.0)
